cancelchain/__init__.py
cancelchain/api.py
cancelchain/api_client.py
cancelchain/application.py
cancelchain/block.py
cancelchain/browser.py
cancelchain/cache.py
cancelchain/chain.py
cancelchain/command.py
cancelchain/config.py
cancelchain/console.py
cancelchain/database.py
cancelchain/exceptions.py
cancelchain/miller.py
cancelchain/milling.py
cancelchain/models.py
cancelchain/node.py
cancelchain/payload.py
cancelchain/schema.py
cancelchain/signals.py
cancelchain/tasks.py
cancelchain/transaction.py
cancelchain/util.py
cancelchain/wallet.py
cancelchain/templates/base.html
cancelchain/templates/block.html
cancelchain/templates/chains.html
cancelchain/templates/index.html
cancelchain/templates/transaction.html
cancelchain-1.4.1.dist-info/METADATA
cancelchain-1.4.1.dist-info/WHEEL
cancelchain-1.4.1.dist-info/entry_points.txt
cancelchain-1.4.1.dist-info/licenses/LICENSE
cancelchain-1.4.1.dist-info/RECORD
