Metadata-Version: 2.1
Name: cancelchain
Version: 1.4.1
Summary: A Blockchain of Accountability, Forgiveness, and Support
Project-URL: Homepage, https://cancelchain.org
Project-URL: Documentation, https://docs.cancelchain.org
Project-URL: Source, https://github.com/cancelchain/cancelchain
Project-URL: Tracker, https://github.com/cancelchain/cancelchain/issues
Author-email: Thomas Bohmbach Jr <tom@cancelchain.org>
License-Expression: MIT
License-File: LICENSE
Keywords: blockchain,flask
Classifier: Development Status :: 5 - Production/Stable
Classifier: Framework :: Flask
Classifier: License :: OSI Approved :: MIT License
Classifier: Operating System :: OS Independent
Classifier: Programming Language :: Python :: 3.9
Classifier: Programming Language :: Python :: 3.10
Classifier: Programming Language :: Python :: 3.11
Classifier: Topic :: Sociology
Requires-Python: >=3.9
Requires-Dist: base58check>=1.0
Requires-Dist: blinker>=1.6
Requires-Dist: celery>=5.3
Requires-Dist: click>=8.1
Requires-Dist: flask-caching>=2.0
Requires-Dist: flask-sqlalchemy>=3.0
Requires-Dist: flask>=2.3
Requires-Dist: gunicorn>=20.1
Requires-Dist: humanfriendly>=10.0
Requires-Dist: marshmallow>=3.19
Requires-Dist: millify>=0.1
Requires-Dist: passlib[argon2]>=1.7
Requires-Dist: pg8000>=1.29
Requires-Dist: pycryptodome>=3.18
Requires-Dist: pyjwt>=2.7
Requires-Dist: pymerkle<5.0,>=4.0
Requires-Dist: python-dotenv>=1.0
Requires-Dist: requests>=2.31
Requires-Dist: rich>=13.4
Requires-Dist: sqlalchemy<2.0
